Metadata-Version: 2.1
Name: serra-cli
Version: 0.1.1
Summary: Simplified Data Pipelines
Home-page: http://github.com
Author: Albert Stanley
Author-email: albert@serra.io
License: tbd
Platform: UNKNOWN
